typewriter/__main__.py
typewriter/writer.py
tl_typewriter-0.2.dist-info/LICENSE
tl_typewriter-0.2.dist-info/METADATA
tl_typewriter-0.2.dist-info/WHEEL
tl_typewriter-0.2.dist-info/entry_points.txt
tl_typewriter-0.2.dist-info/top_level.txt
tl_typewriter-0.2.dist-info/RECORD
